cdklabs/deploy_time_build/__init__.py
cdklabs/deploy_time_build/py.typed
cdklabs/deploy_time_build/_jsii/__init__.py
cdklabs/deploy_time_build/_jsii/deploy-time-build@0.0.4.jsii.tgz
cdklabs_deploy_time_build-0.0.4.dist-info/LICENSE
cdklabs_deploy_time_build-0.0.4.dist-info/METADATA
cdklabs_deploy_time_build-0.0.4.dist-info/WHEEL
cdklabs_deploy_time_build-0.0.4.dist-info/top_level.txt
cdklabs_deploy_time_build-0.0.4.dist-info/RECORD
