Metadata-Version: 2.1
Name: cdklabs.deploy-time-build
Version: 0.0.4
Summary: Run build on CDK deployment time.
Home-page: https://github.com/cdklabs/deploy-time-build.git
Author: Amazon Web Services<aws-cdk-dev@amazon.com>
License: Apache-2.0
Project-URL: Source, https://github.com/cdklabs/deploy-time-build.git
Classifier: Intended Audience :: Developers
Classifier: Operating System :: OS Independent
Classifier: Programming Language :: JavaScript
Classifier: Programming Language :: Python :: 3 :: Only
Classifier: Programming Language :: Python :: 3.9
Classifier: Programming Language :: Python :: 3.10
Classifier: Programming Language :: Python :: 3.11
Classifier: Typing :: Typed
Classifier: Development Status :: 4 - Beta
Classifier: License :: OSI Approved
Requires-Python: ~=3.9
License-File: LICENSE
Requires-Dist: aws-cdk-lib <3.0.0,>=2.38.0
Requires-Dist: constructs <11.0.0,>=10.0.5
Requires-Dist: jsii <2.0.0,>=1.125.0
Requires-Dist: publication >=0.0.3
Requires-Dist: typeguard ==2.13.3
